formatfusion/__main__.py
formatfusion/commands/__init__.py
formatfusion/commands/cmd_image.py
formatfusion/commands/cmd_yaml.py
formatfusion/core/__init__.py
formatfusion/core/base.py
formatfusion/core/image.py
formatfusion/core/json_and_yaml.py
formatfusion/helpers.py
formatfusion/main.py
cli_format_fusion-0.1.0.dist-info/entry_points.txt
cli_format_fusion-0.1.0.dist-info/LICENSE
cli_format_fusion-0.1.0.dist-info/METADATA
cli_format_fusion-0.1.0.dist-info/WHEEL
cli_format_fusion-0.1.0.dist-info/RECORD
