Metadata-Version: 2.1
Name: cli-format-fusion
Version: 0.1.0
Summary: A mini conversion tool
Author: R00kie
Author-email: driftworks2013@yandex.ru
Requires-Python: >=3.11.0,<4.0.0
Classifier: Programming Language :: Python :: 3
Classifier: Programming Language :: Python :: 3.11
Classifier: Programming Language :: Python :: 3.12
Classifier: Programming Language :: Python :: 3.13
Requires-Dist: docopt (>=0.6.2,<0.7.0)
Requires-Dist: pyyaml (>=6.0.2,<7.0.0)
Project-URL: Homepage, https://github.com/Nottezz/format-fusion-cli
Project-URL: Issues, https://github.com/Nottezz/format-fusion-cli/issues
